{
  "profile_id": "run2_ai",
  "extends": "story_mix.json",
  "_notes": [
    "12:00 run — AI / Tech / Science channel (aggressive version 2026-04-14).",
    "",
    "Previous version (v1) was too gentle: entertainment got 14% of target",
    "and topic_boost 0.9, which could not overcome the 50x hotness gap",
    "between bilibili video (hotness 500+) and hackernews tech (hotness 5-20).",
    "Result: 57% entertainment, 1.6% AI in the live set 80. Fix:",
    "",
    "  1. category_mix: entertainment/sports/world = 0. All budget goes to",
    "     tech/ai/science/business + necessary politics/society filler",
    "     (at the 2x feasibility cap).",
    "",
    "  2. topic_boosts: crush entertainment to 0.05 (20x penalty),",
    "     sports to 0.1, boost ai to 3.0, tech to 2.5, science to 2.0.",
    "",
    "  3. platform_weight_overrides: crush video platforms (bilibili,",
    "     youtube, nicovideo) to 0.1 to neutralize their unnormalized",
    "     hotness scale. Boost hackernews/devto/lobsters/stackoverflow",
    "     (text-heavy tech platforms) to 1.5-2.0.",
    "",
    "Feasibility ratios vs 2x cap:",
    "  technology 0.14/0.071=1.97",
    "  business   0.13/0.066=1.97",
    "  ai         0.07/0.039=1.79",
    "  science    0.06/0.035=1.71",
    "  politics   0.30/0.357=0.84",
    "  society    0.30/0.233=1.29",
    "  world/entertainment/sports: 0.00 (skipped)",
    "All within gate."
  ],

  "soft_targets": {
    "category_mix": {
      "politics":      0.30,
      "society":       0.30,
      "technology":    0.14,
      "business":      0.13,
      "ai":            0.07,
      "science":       0.06,
      "entertainment": 0.00,
      "sports":        0.00,
      "world":         0.00
    }
  },

  "ranking": {
    "topic_boosts": {
      "ai":            3.00,
      "technology":    2.50,
      "science":       2.00,
      "business":      1.50,
      "society":       0.60,
      "politics":      0.50,
      "world":         0.40,
      "sports":        0.10,
      "entertainment": 0.05
    },
    "platform_weight_overrides": {
      "bilibili":      0.10,
      "youtube":       0.10,
      "nicovideo":     0.10,
      "hackernews":    2.00,
      "devto":         1.80,
      "lobsters":      1.80,
      "stackoverflow": 1.50,
      "paperswithcode": 2.00,
      "arxiv_ai_rss":  2.00,
      "weibo":         1.00,
      "baidu":         1.00,
      "zhihu":         1.00,
      "google_trends": 0.20,
      "wikipedia":     0.50,
      "news_rss":      0.45,
      "chinatimes":    0.50,
      "hk01":          0.50,
      "ettoday":       0.40,
      "36kr":          1.20
    }
  }
}
